{
  "metadata": {
    "version": "1.0",
    "generated": "2024-07-15",
    "description": "Synthetic maintenance logs organized into 3 sequential failure stories for NexusOps AI training data",
    "total_entries": 27,
    "stories": [
      "Story 1: Carrier 30RAP condenser fouling cascade (E3 -> A6 -> E3)",
      "Story 2: York YVAA refrigerant loss and compressor thermal damage (U0 -> E5)",
      "Story 3: Carrier 30RAP low-ambient startup with crankcase heater failure (103 -> E5)"
    ]
  },
  "logs": [
    {
      "id": "LOG-001",
      "story": 1,
      "sequence": 1,
      "timestamp": "2024-05-10T08:23:00",
      "asset_id": "CAR-30RAP-UNIT-04",
      "model": "Carrier 30RAP",
      "site": "Greenfield Industrial Park - Building B",
      "technician": "M. Rodriguez",
      "event_type": "alarm",
      "error_code": "E3",
      "title": "E3 High Pressure Trip — First Occurrence",
      "description": "Unit 04 went into E3 lockout at 08:23. Ambient temperature was 98°F. Operator reported the unit had been running for 6 hours prior without issue. Manual reset performed without investigation. Unit restarted.",
      "discharge_pressure_psig": 662,
      "suction_pressure_psig": 158,
      "ambient_temp_f": 98,
      "resolution": "Manual reset — no root cause identified",
      "outcome": "INCOMPLETE — unit restarted without investigation"
    },
    {
      "id": "LOG-002",
      "story": 1,
      "sequence": 2,
      "timestamp": "2024-05-10T11:45:00",
      "asset_id": "CAR-30RAP-UNIT-04",
      "model": "Carrier 30RAP",
      "site": "Greenfield Industrial Park - Building B",
      "technician": "M. Rodriguez",
      "event_type": "alarm",
      "error_code": "E3",
      "title": "E3 High Pressure Trip — Second Occurrence Same Day",
      "description": "Unit 04 tripped on E3 again only 3 hours after manual reset. Ambient dropped to 94°F but unit still tripped. Technician noted one condenser fan was not rotating during inspection — confirmed A6 fan motor fault was also present but suppressed alarm.",
      "discharge_pressure_psig": 671,
      "suction_pressure_psig": 155,
      "ambient_temp_f": 94,
      "resolution": "Fan #3 found stationary. Fan motor overload tripped. Reset overload.",
      "outcome": "PARTIAL — overload reset but motor health not verified"
    },
    {
      "id": "LOG-003",
      "story": 1,
      "sequence": 3,
      "timestamp": "2024-05-11T09:15:00",
      "asset_id": "CAR-30RAP-UNIT-04",
      "model": "Carrier 30RAP",
      "site": "Greenfield Industrial Park - Building B",
      "technician": "J. Williams",
      "event_type": "service_call",
      "error_code": "A6",
      "title": "A6 Fan Motor Fault — Service Investigation",
      "description": "Dispatched for active A6 fault on Fan #3. Found run capacitor failed (measured 6µF vs 25µF nameplate rating). Also noted condenser coil heavily fouled — approximately 40% blockage by cottonwood seeds and debris. Both conditions contributing to elevated head pressure.",
      "fan_capacitor_measured_uf": 6,
      "fan_capacitor_rated_uf": 25,
      "condenser_coil_blockage_pct": 40,
      "resolution": "Replaced run capacitor (25µF/370VAC). Cleaned condenser coil with Nu-Brite coil cleaner.",
      "outcome": "RESOLVED — both root causes addressed"
    },
    {
      "id": "LOG-004",
      "story": 1,
      "sequence": 4,
      "timestamp": "2024-05-11T13:30:00",
      "asset_id": "CAR-30RAP-UNIT-04",
      "model": "Carrier 30RAP",
      "site": "Greenfield Industrial Park - Building B",
      "technician": "J. Williams",
      "event_type": "verification",
      "error_code": null,
      "title": "Post-Repair Verification — Unit Running Stable",
      "description": "Performed 2-hour post-repair monitoring run. All 4 condenser fans operating correctly at full amperage. Discharge pressure normalized to 385 psig at 91°F ambient. Subcooling measured at 11°F (within spec). System performance restored to baseline.",
      "discharge_pressure_psig": 385,
      "suction_pressure_psig": 168,
      "ambient_temp_f": 91,
      "subcooling_f": 11,
      "all_fans_running": true,
      "resolution": "Verification complete — unit operating within specifications",
      "outcome": "RESOLVED"
    },
    {
      "id": "LOG-005",
      "story": 1,
      "sequence": 5,
      "timestamp": "2024-05-25T07:00:00",
      "asset_id": "CAR-30RAP-UNIT-04",
      "model": "Carrier 30RAP",
      "site": "Greenfield Industrial Park - Building B",
      "technician": "M. Rodriguez",
      "event_type": "preventive_maintenance",
      "error_code": null,
      "title": "Preventive Maintenance — Condenser Inspection Added to PM Schedule",
      "description": "Following the May 10-11 failure sequence, condenser coil inspection and cleaning added to monthly PM checklist. All four fan motor capacitors measured and documented as baseline. No faults present.",
      "condenser_coil_blockage_pct": 5,
      "fan_capacitors_measured": [24.8, 25.1, 25.2, 24.9],
      "resolution": "Preventive maintenance completed — coil clean, capacitors at spec",
      "outcome": "PREVENTIVE — no active faults"
    },
    {
      "id": "LOG-006",
      "story": 1,
      "sequence": 6,
      "timestamp": "2024-06-15T16:45:00",
      "asset_id": "CAR-30RAP-UNIT-04",
      "model": "Carrier 30RAP",
      "site": "Greenfield Industrial Park - Building B",
      "technician": "J. Williams",
      "event_type": "inspection",
      "error_code": null,
      "title": "Monthly PM — Unit Clear, Lessons Learned Documented",
      "description": "Monthly PM inspection completed. Condenser coil at 8% blockage after one month — acceptable. All fan motors at nameplate amperage. Recommended increasing PM frequency to monthly during cottonwood season (April-June). Root cause analysis of May failure closed.",
      "condenser_coil_blockage_pct": 8,
      "resolution": "PM complete — no corrective action required",
      "outcome": "PREVENTIVE"
    },
    {
      "id": "LOG-007",
      "story": 2,
      "sequence": 1,
      "timestamp": "2024-06-03T06:00:00",
      "asset_id": "YORK-YVAA-UNIT-07",
      "model": "York YVAA",
      "site": "Meridian Data Center - Chiller Plant",
      "technician": "D. Chen",
      "event_type": "alarm",
      "error_code": "U0",
      "title": "U0 Refrigerant Loss — Early Morning Alarm",
      "description": "BMS alarm triggered for York YVAA Unit 07 at 06:00. Suction pressure monitoring showed progressive decline over 48-hour period from 178 psig to 118 psig on R-134a system. U0 alarm activated when pressure dropped below 125 psig threshold. Unit continued to operate in degraded mode.",
      "suction_pressure_psig": 118,
      "suction_pressure_setpoint_psig": 125,
      "pressure_trend_48h": "declining",
      "resolution": "Alarm acknowledged — leak detection inspection scheduled for next business day",
      "outcome": "DEFERRED — high-risk decision to defer service"
    },
    {
      "id": "LOG-008",
      "story": 2,
      "sequence": 2,
      "timestamp": "2024-06-04T08:30:00",
      "asset_id": "YORK-YVAA-UNIT-07",
      "model": "York YVAA",
      "site": "Meridian Data Center - Chiller Plant",
      "technician": "D. Chen",
      "event_type": "service_call",
      "error_code": "U0",
      "title": "U0 Leak Detection Investigation",
      "description": "Arrived on site for U0 investigation. Suction pressure now at 96 psig — significant drop overnight. Performed electronic leak detection scan. Found active leak at left evaporator header brazed joint — detector alarming at >500 ppm. Estimated leak rate ~3 lbs/day based on pressure decay.",
      "suction_pressure_psig": 96,
      "leak_location": "Evaporator left header brazed joint",
      "leak_rate_lbs_per_day": 3,
      "leak_ppm_detected": ">500",
      "discharge_temp_f": 228,
      "resolution": "Leak located. Parts ordered for repair. Decision made to continue operating overnight with monitoring.",
      "outcome": "PARTIAL — leak found but not repaired; risky continued operation"
    },
    {
      "id": "LOG-009",
      "story": 2,
      "sequence": 3,
      "timestamp": "2024-06-04T23:15:00",
      "asset_id": "YORK-YVAA-UNIT-07",
      "model": "York YVAA",
      "site": "Meridian Data Center - Chiller Plant",
      "technician": "BMS System (auto-generated)",
      "event_type": "alarm",
      "error_code": "E5",
      "title": "E5 High Discharge Temperature — Critical Alarm",
      "description": "E5 fault activated at 23:15 with discharge temperature reaching 248°F — 8°F above the 240°F trip setpoint. Compressor entered thermal protection shutdown. Discharge pressure was 196 psig (low for load conditions, confirming very low charge). Data center cooling load switched to secondary chiller.",
      "discharge_temp_f": 248,
      "trip_setpoint_f": 240,
      "discharge_pressure_psig": 196,
      "suction_pressure_psig": 58,
      "suction_superheat_f": 35,
      "resolution": "E5 lockout — unit offline. Emergency technician dispatched.",
      "outcome": "CRITICAL — compressor thermal damage likely"
    },
    {
      "id": "LOG-010",
      "story": 2,
      "sequence": 4,
      "timestamp": "2024-06-05T01:30:00",
      "asset_id": "YORK-YVAA-UNIT-07",
      "model": "York YVAA",
      "site": "Meridian Data Center - Chiller Plant",
      "technician": "K. Patel",
      "event_type": "emergency_service",
      "error_code": "E5",
      "title": "Emergency Response — Post E5 Compressor Assessment",
      "description": "Emergency technician arrived at 01:30. Unit completely off. Compressor casing temperature at 182°F (still cooling from trip at 23:15). Oil analysis sample taken — will indicate acid formation if compressor valves damaged. Refrigerant recovered (18 lbs R-134a recovered vs 48 lbs nameplate charge — confirms ~30 lbs lost). Evaporator header leak confirmed and repair initiated.",
      "refrigerant_recovered_lbs": 18,
      "nameplate_charge_lbs": 48,
      "estimated_leaked_lbs": 30,
      "compressor_case_temp_f": 182,
      "resolution": "Brazed joint re-brazed with nitrogen purge. Nitrogen pressure test initiated at 100 psig.",
      "outcome": "REPAIR IN PROGRESS"
    },
    {
      "id": "LOG-011",
      "story": 2,
      "sequence": 5,
      "timestamp": "2024-06-05T10:00:00",
      "asset_id": "YORK-YVAA-UNIT-07",
      "model": "York YVAA",
      "site": "Meridian Data Center - Chiller Plant",
      "technician": "K. Patel",
      "event_type": "service_call",
      "error_code": null,
      "title": "Nitrogen Pressure Test Pass — Vacuum and Recharge",
      "description": "24-hour nitrogen pressure test at 100 psig passed — no pressure loss detected. Pulled vacuum to 285 microns over 4 hours. Oil analysis results returned: acid number elevated (0.08 mg KOH/g vs <0.05 limit) — indicates early stage burnout/acid formation. Decision made to replace oil and install acid filter. Recharged with 48 lbs virgin R-134a.",
      "nitrogen_test_result": "PASS",
      "vacuum_microns": 285,
      "oil_acid_number": 0.08,
      "oil_acid_limit": 0.05,
      "refrigerant_added_lbs": 48,
      "resolution": "Oil changed, acid filter installed, recharged to spec. Compressor test run initiated.",
      "outcome": "RESOLVED WITH CORRECTIVE ACTION — increased inspection frequency required"
    },
    {
      "id": "LOG-012",
      "story": 2,
      "sequence": 6,
      "timestamp": "2024-06-06T08:00:00",
      "asset_id": "YORK-YVAA-UNIT-07",
      "model": "York YVAA",
      "site": "Meridian Data Center - Chiller Plant",
      "technician": "K. Patel",
      "event_type": "verification",
      "error_code": null,
      "title": "Post-Repair 24h Monitoring — System Stable",
      "description": "24-hour post-repair monitoring complete. Suction pressure stable at 183 psig (within spec). Discharge temperature at 178°F (well below 240°F limit). Subcooling 12°F, superheat 9°F — system performing correctly. Oil sample retested at 72h: acid number 0.04 (within limit). Root cause analysis completed — additional PM added for quarterly evaporator leak checks.",
      "suction_pressure_psig": 183,
      "discharge_temp_f": 178,
      "subcooling_f": 12,
      "superheat_f": 9,
      "oil_acid_number_72h": 0.04,
      "resolution": "Full resolution confirmed. RCA completed and filed.",
      "outcome": "RESOLVED"
    },
    {
      "id": "LOG-013",
      "story": 2,
      "sequence": 7,
      "timestamp": "2024-07-01T09:00:00",
      "asset_id": "YORK-YVAA-UNIT-07",
      "model": "York YVAA",
      "site": "Meridian Data Center - Chiller Plant",
      "technician": "D. Chen",
      "event_type": "preventive_maintenance",
      "error_code": null,
      "title": "New PM Protocol — Quarterly Refrigerant Leak Survey",
      "description": "First quarterly refrigerant leak survey per updated PM protocol. Electronic leak detection scan of all brazed joints and service connections. No leaks detected. Refrigerant charge verified by subcooling method. Sight glass clear. Incident corrective actions verified as sustained.",
      "leak_detected": false,
      "subcooling_f": 11,
      "sight_glass": "clear",
      "resolution": "PM complete — no issues found",
      "outcome": "PREVENTIVE"
    },
    {
      "id": "LOG-014",
      "story": 3,
      "sequence": 1,
      "timestamp": "2024-01-08T05:30:00",
      "asset_id": "CAR-30RAP-UNIT-11",
      "model": "Carrier 30RAP",
      "site": "Northgate Chemical Plant - Utility Building",
      "technician": "BMS System (auto-generated)",
      "event_type": "alarm",
      "error_code": "103",
      "title": "103 Prestart Temperature Alert — Cold Weather Startup",
      "description": "Unit 11 attempted startup at 05:30 after overnight setback. Ambient temperature was 28°F — below the 40°F low ambient lockout setting. Controller generated Code 103 and delayed startup. BMS operator attempted remote reset 3 times over 30-minute period. Each reset failed as ambient remained below threshold.",
      "ambient_temp_f": 28,
      "low_ambient_lockout_f": 40,
      "startup_attempts": 3,
      "resolution": "103 alarm acknowledged. Facility operator notified. Waiting for ambient rise.",
      "outcome": "MONITORING — expected normal behavior at this ambient"
    },
    {
      "id": "LOG-015",
      "story": 3,
      "sequence": 2,
      "timestamp": "2024-01-08T10:15:00",
      "asset_id": "CAR-30RAP-UNIT-11",
      "model": "Carrier 30RAP",
      "site": "Northgate Chemical Plant - Utility Building",
      "technician": "T. Okonkwo",
      "event_type": "service_call",
      "error_code": "103",
      "title": "103 Investigation — Ambient Now 46°F But Unit Still Failing to Start",
      "description": "Technician dispatched when unit failed to start even after ambient reached 46°F (above 40°F lockout threshold). Controller still showing Code 103. Investigation revealed crankcase heater on Compressor Bank A had failed — resistance measured as open circuit (infinite ohms). Compressor oil had not been maintained at proper temperature overnight.",
      "ambient_temp_f": 46,
      "crankcase_heater_resistance_ohms": "OPEN",
      "crankcase_heater_expected_ohms": 1840,
      "crankcase_heater_voltage_vac": 0,
      "compressor_oil_temp_f": 38,
      "resolution": "Crankcase heater failure confirmed. Replacement part ordered.",
      "outcome": "PARTIAL — root cause found, repair pending"
    },
    {
      "id": "LOG-016",
      "story": 3,
      "sequence": 3,
      "timestamp": "2024-01-08T14:30:00",
      "asset_id": "CAR-30RAP-UNIT-11",
      "model": "Carrier 30RAP",
      "site": "Northgate Chemical Plant - Utility Building",
      "technician": "T. Okonkwo",
      "event_type": "service_call",
      "error_code": "103",
      "title": "Crankcase Heater Replacement — Temporary Workaround",
      "description": "Replacement crankcase heater (240V, 300W) installed per Carrier service manual. Verified heater draws 1.25A at 240VAC (within spec). Oil temperature rising. Elected to wait 8 hours before attempting startup to ensure adequate oil temperature per Carrier startup guideline. External heater blanket applied as supplemental measure.",
      "crankcase_heater_amps": 1.25,
      "crankcase_heater_watts": 300,
      "crankcase_heater_voltage_vac": 240,
      "wait_period_hours": 8,
      "resolution": "Heater replaced. 8-hour pre-heat protocol initiated.",
      "outcome": "REPAIR IN PROGRESS"
    },
    {
      "id": "LOG-017",
      "story": 3,
      "sequence": 4,
      "timestamp": "2024-01-08T22:45:00",
      "asset_id": "CAR-30RAP-UNIT-11",
      "model": "Carrier 30RAP",
      "site": "Northgate Chemical Plant - Utility Building",
      "technician": "T. Okonkwo",
      "event_type": "alarm",
      "error_code": "E5",
      "title": "E5 High Discharge Temperature on First Startup After 103 — Oil Migration Suspected",
      "description": "After 8-hour pre-heat and oil temperature reaching 68°F, unit was started. Within 4 minutes, E5 fault activated. Discharge temperature spiked to 258°F rapidly — faster than typical thermal overload. This behavior consistent with refrigerant-diluted oil (oil migration during extended cold soak — crankcase heater had likely been failing for weeks). Compressor locked out.",
      "discharge_temp_f": 258,
      "time_to_trip_minutes": 4,
      "oil_temp_at_startup_f": 68,
      "resolution": "E5 lockout. Suspect oil-refrigerant dilution from extended crankcase heater failure.",
      "outcome": "CRITICAL — suspected compressor damage from oil dilution"
    },
    {
      "id": "LOG-018",
      "story": 3,
      "sequence": 5,
      "timestamp": "2024-01-09T09:00:00",
      "asset_id": "CAR-30RAP-UNIT-11",
      "model": "Carrier 30RAP",
      "site": "Northgate Chemical Plant - Utility Building",
      "technician": "T. Okonkwo",
      "event_type": "service_call",
      "error_code": "E5",
      "title": "Oil Analysis and Compressor Assessment",
      "description": "Oil analysis sample drawn from compressor bank A. Visual inspection of oil: milky/opaque color indicating refrigerant contamination (oil-refrigerant mixture). Suction pressure measured at 92 psig (low for R-410A at 65°F ambient — indicates refrigerant trapped in oil). Compression ratio measured at 2.8 vs expected 4.1 — confirms compressor valve efficiency loss.",
      "oil_color": "milky/opaque",
      "oil_contamination": "refrigerant dilution",
      "suction_pressure_psig": 92,
      "compression_ratio_actual": 2.8,
      "compression_ratio_expected": 4.1,
      "resolution": "Oil change performed. Extended 16-hour pre-heat protocol initiated at higher oil temperature target (>80°F).",
      "outcome": "PARTIAL — compressor efficiency degraded; monitoring required"
    },
    {
      "id": "LOG-019",
      "story": 3,
      "sequence": 6,
      "timestamp": "2024-01-10T08:00:00",
      "asset_id": "CAR-30RAP-UNIT-11",
      "model": "Carrier 30RAP",
      "site": "Northgate Chemical Plant - Utility Building",
      "technician": "T. Okonkwo",
      "event_type": "verification",
      "error_code": null,
      "title": "Second Startup Attempt — Partial Success",
      "description": "After 16-hour pre-heat with oil temperature at 84°F, unit restarted. No E5 fault on startup. Discharge temperature stabilized at 198°F (below 220°F alarm). However, compression ratio still at 3.2 vs expected 4.1 — efficiency loss of ~22%. Chilled water setpoint raised from 44°F to 48°F to reduce compressor load. Unit running in degraded but stable mode.",
      "oil_temp_at_startup_f": 84,
      "discharge_temp_f": 198,
      "compression_ratio": 3.2,
      "efficiency_loss_pct": 22,
      "chilled_water_setpoint_f": 48,
      "resolution": "Unit running in degraded mode. Compressor replacement quote requested from Carrier.",
      "outcome": "STABLE BUT DEGRADED"
    },
    {
      "id": "LOG-020",
      "story": 3,
      "sequence": 7,
      "timestamp": "2024-01-15T11:00:00",
      "asset_id": "CAR-30RAP-UNIT-11",
      "model": "Carrier 30RAP",
      "site": "Northgate Chemical Plant - Utility Building",
      "technician": "Carrier Field Engineering",
      "event_type": "engineering_assessment",
      "error_code": null,
      "title": "Carrier Engineering Assessment — Compressor Replacement Required",
      "description": "Carrier field engineer assessed Unit 11. Confirmed compressor scroll set damage from oil dilution operation. Compressor bank A to be replaced (remanufactured scroll set available in 3 weeks). Until then, unit operating on Compressor Bank B only at 50% capacity. Crankcase heater interlock relay installed to prevent startup if heater circuit fails.",
      "compressor_bank_a_status": "failed — scheduled replacement",
      "compressor_bank_b_status": "operational at 50% capacity",
      "replacement_lead_time_weeks": 3,
      "corrective_action": "Crankcase heater interlock relay installed",
      "resolution": "Engineering assessment complete. Compressor replacement scheduled.",
      "outcome": "LONG-TERM REPAIR IN PROGRESS"
    },
    {
      "id": "LOG-021",
      "story": 3,
      "sequence": 8,
      "timestamp": "2024-02-05T09:00:00",
      "asset_id": "CAR-30RAP-UNIT-11",
      "model": "Carrier 30RAP",
      "site": "Northgate Chemical Plant - Utility Building",
      "technician": "Carrier Service Team",
      "event_type": "major_repair",
      "error_code": null,
      "title": "Compressor Bank A Replacement — Full System Restoration",
      "description": "Remanufactured scroll compressor bank A installed per Carrier service bulletin. Refrigerant fully recovered (46 lbs), new filter-dryer and oil separator installed. System recharged with virgin R-410A (52 lbs to nameplate). System commissioned at full capacity. Discharge temperature 182°F, compression ratio 4.0 (within spec). Full load test complete.",
      "refrigerant_recovered_lbs": 46,
      "refrigerant_added_lbs": 52,
      "discharge_temp_f": 182,
      "compression_ratio": 4.0,
      "chilled_water_setpoint_f": 44,
      "resolution": "Full restoration complete. Unit back at nameplate capacity.",
      "outcome": "RESOLVED"
    },
    {
      "id": "LOG-022",
      "story": 3,
      "sequence": 9,
      "timestamp": "2024-02-05T15:00:00",
      "asset_id": "CAR-30RAP-UNIT-11",
      "model": "Carrier 30RAP",
      "site": "Northgate Chemical Plant - Utility Building",
      "technician": "T. Okonkwo",
      "event_type": "preventive_maintenance",
      "error_code": null,
      "title": "Lessons Learned — PM Protocol Updated",
      "description": "Post-incident review completed. Root cause traced to crankcase heater failure going undetected for an estimated 4-6 weeks (no heater health monitoring in prior PM). Corrective actions: 1) Monthly crankcase heater resistance check added to winter PM. 2) Startup interlock relay installed. 3) Low ambient startup pre-heat procedure updated to require 80°F oil temp minimum.",
      "lessons_learned": [
        "Crankcase heater failure must be detected proactively, not reactively",
        "103 alert in cold weather should always trigger crankcase heater inspection",
        "Oil temperature must be verified before startup, not just ambient temperature"
      ],
      "pm_changes_made": [
        "Monthly crankcase heater resistance check (target: 1840 ohms ±10%)",
        "Startup interlock relay on heater circuit",
        "Updated cold weather startup checklist"
      ],
      "resolution": "PM protocol updated. Incident closed.",
      "outcome": "RESOLVED — systemic improvement implemented"
    },
    {
      "id": "LOG-023",
      "story": 1,
      "sequence": 7,
      "timestamp": "2024-07-20T14:00:00",
      "asset_id": "CAR-30RAP-UNIT-04",
      "model": "Carrier 30RAP",
      "site": "Greenfield Industrial Park - Building B",
      "technician": "M. Rodriguez",
      "event_type": "alarm",
      "error_code": "E3",
      "title": "E3 Recurrence — Fan #2 Bearing Failure",
      "description": "Unit 04 E3 recurrence despite clean coil from June PM. Inspection found Fan #2 motor bearing seized — motor running but at very low RPM (audible grinding). Fan blade visually stationary. Motor amperage on phase 1 was 18.5A vs 4.2A nameplate FLA — motor drawing excessive current through locked rotor.",
      "discharge_pressure_psig": 645,
      "fan_2_amperage_a": 18.5,
      "fan_2_nameplate_fla_a": 4.2,
      "fan_2_rpm_observed": "near zero",
      "resolution": "Motor overload tripped. Motor replaced (TEFC, 1HP, 460V, 1075RPM). Overload relay reset.",
      "outcome": "RESOLVED — fan motor replaced"
    },
    {
      "id": "LOG-024",
      "story": 2,
      "sequence": 8,
      "timestamp": "2024-09-15T11:30:00",
      "asset_id": "YORK-YVAA-UNIT-07",
      "model": "York YVAA",
      "site": "Meridian Data Center - Chiller Plant",
      "technician": "D. Chen",
      "event_type": "inspection",
      "error_code": null,
      "title": "Quarterly Refrigerant Survey — Minor Leak Found at Compressor Discharge Service Valve",
      "description": "Quarterly refrigerant survey identified minor leak at compressor discharge service valve packing. Leak rate estimated at 0.05 lbs/day via bubble test. Suction pressure trending slightly low (175 psig vs 183 psig baseline) confirming gradual loss. Valve packing replaced during survey.",
      "suction_pressure_psig": 175,
      "suction_pressure_baseline_psig": 183,
      "leak_location": "Compressor discharge service valve packing",
      "estimated_leak_rate_lbs_per_day": 0.05,
      "resolution": "Valve packing replaced. Leak test confirmed sealed. No refrigerant addition required.",
      "outcome": "RESOLVED — proactive detection prevented major incident"
    },
    {
      "id": "LOG-025",
      "story": 3,
      "sequence": 10,
      "timestamp": "2024-11-15T08:00:00",
      "asset_id": "CAR-30RAP-UNIT-11",
      "model": "Carrier 30RAP",
      "site": "Northgate Chemical Plant - Utility Building",
      "technician": "T. Okonkwo",
      "event_type": "preventive_maintenance",
      "error_code": null,
      "title": "Pre-Winter PM — Crankcase Heater Verified, Cold Weather Startup Procedure Reviewed",
      "description": "Pre-winter PM completed for Unit 11 ahead of cold season. Crankcase heater resistance measured at 1847 ohms (within 10% of 1840 spec). Startup interlock relay tested — confirmed it prevents startup if heater circuit opens. Cold weather startup procedure reviewed with facility operator. No issues identified.",
      "crankcase_heater_resistance_ohms": 1847,
      "crankcase_heater_spec_ohms": 1840,
      "interlock_test_result": "PASS",
      "resolution": "Pre-winter PM complete — unit ready for cold weather operations",
      "outcome": "PREVENTIVE — no active issues"
    },
    {
      "id": "LOG-026",
      "story": 1,
      "sequence": 8,
      "timestamp": "2024-08-05T09:30:00",
      "asset_id": "CAR-30RAP-UNIT-04",
      "model": "Carrier 30RAP",
      "site": "Greenfield Industrial Park - Building B",
      "technician": "J. Williams",
      "event_type": "preventive_maintenance",
      "error_code": null,
      "title": "Annual PM — Full Refrigerant System Check",
      "description": "Annual PM completed. Refrigerant system check: subcooling 11°F, superheat 9°F, sight glass clear. Condenser coil at 12% blockage — cleaned. All 4 fan motors amperage verified: 4.1A, 4.2A, 4.1A, 4.0A (all within spec). No leaks detected by electronic leak detector. Compressor oil sample sent for analysis.",
      "subcooling_f": 11,
      "superheat_f": 9,
      "condenser_coil_blockage_pct": 12,
      "fan_amperages_a": [4.1, 4.2, 4.1, 4.0],
      "leak_detected": false,
      "resolution": "Annual PM complete — all systems nominal",
      "outcome": "PREVENTIVE"
    },
    {
      "id": "LOG-027",
      "story": 2,
      "sequence": 9,
      "timestamp": "2024-11-01T10:00:00",
      "asset_id": "YORK-YVAA-UNIT-07",
      "model": "York YVAA",
      "site": "Meridian Data Center - Chiller Plant",
      "technician": "D. Chen",
      "event_type": "preventive_maintenance",
      "error_code": null,
      "title": "Annual PM — 18-Month Post-Incident Audit",
      "description": "18-month post-incident audit for YORK-YVAA-UNIT-07. System performing at full capacity. Refrigerant charge verified at nameplate. Oil acid number 0.03 (well within <0.05 limit). No leaks detected across 47 inspection points. Microgateway+ controller event log reviewed — zero refrigerant-related alarms in past 4 months. System declared fully rehabilitated.",
      "refrigerant_charge_lbs": 48,
      "oil_acid_number": 0.03,
      "leak_inspection_points": 47,
      "leaks_found": 0,
      "alarm_free_days": 120,
      "resolution": "Annual PM complete — system fully rehabilitated",
      "outcome": "PREVENTIVE — long-term stability confirmed"
    }
  ]
}
